chatter_ai/__init__.py
chatter_ai_7b-1.0.1.dist-info/METADATA
chatter_ai_7b-1.0.1.dist-info/WHEEL
chatter_ai_7b-1.0.1.dist-info/top_level.txt
chatter_ai_7b-1.0.1.dist-info/RECORD
