Metadata-Version: 2.1
Name: chatter-ai-7b
Version: 1.0.1
Summary: A chatter AI.
Requires-Dist: requests
